pyams_auth_apikey/__init__.py
pyams_auth_apikey/include.py
pyams_auth_apikey/interfaces.py
pyams_auth_apikey/plugin.py
pyams_auth_apikey/doctests/README.rst
pyams_auth_apikey/locales/pyams_auth_apikey.pot
pyams_auth_apikey/locales/fr/LC_MESSAGES/pyams_auth_apikey.mo
pyams_auth_apikey/locales/fr/LC_MESSAGES/pyams_auth_apikey.po
pyams_auth_apikey/tests/__init__.py
pyams_auth_apikey/tests/test_utilsdocs.py
pyams_auth_apikey/tests/test_utilsdocstrings.py
pyams_auth_apikey/zmi/__init__.py
pyams_auth_apikey/zmi/container.py
pyams_auth_apikey/zmi/interfaces.py
pyams_auth_apikey/zmi/plugin.py
pyams_auth_apikey-2.1.2.dist-info/LICENSE
pyams_auth_apikey-2.1.2.dist-info/METADATA
pyams_auth_apikey-2.1.2.dist-info/WHEEL
pyams_auth_apikey-2.1.2.dist-info/namespace_packages.txt
pyams_auth_apikey-2.1.2.dist-info/top_level.txt
pyams_auth_apikey-2.1.2.dist-info/RECORD
