Metadata-Version: 2.1
Name: pyams-auth-apikey
Version: 2.1.2
Summary: PyAMS authentication module using API keys
Home-page: https://pyams.readthedocs.io
Author: Thierry Florac
Author-email: tflorac@ulthar.net
License: ZPL
Keywords: Pyramid PyAMS
Classifier: License :: OSI Approved :: Zope Public License
Classifier: Development Status :: 4 - Beta
Classifier: Programming Language :: Python
Classifier: Framework :: Pyramid
Classifier: Topic :: Software Development :: Libraries :: Python Modules
License-File: LICENSE
Requires-Dist: setuptools
Requires-Dist: ZODB
Requires-Dist: persistent
Requires-Dist: pyams-security
Requires-Dist: pyams-utils
Requires-Dist: pyramid >=2.0.0
Requires-Dist: zope.container
Requires-Dist: zope.interface
Requires-Dist: zope.schema
Provides-Extra: test
Requires-Dist: pyams-form ; extra == 'test'
Requires-Dist: pyams-layer ; extra == 'test'
Requires-Dist: pyams-security-views ; extra == 'test'
Requires-Dist: pyams-site ; extra == 'test'
Requires-Dist: pyams-skin >=1.9.0 ; extra == 'test'
Requires-Dist: pyams-viewlet ; extra == 'test'
Requires-Dist: pyams-zmi ; extra == 'test'
Requires-Dist: pyramid-zodbconn ; extra == 'test'
